{
  "body_part": "hairstyle",
  "attire": [
    {"type": "bob cut", "country": "neutral", "description": "short, straight cut around the head"},
    {"type": "pixie cut", "country": "neutral", "description": "very short, cropped style"},
    {"type": "afro", "country": "Africa", "description": "rounded, voluminous natural curls"},
    {"type": "cornrows", "country": "Africa", "description": "tight, braided rows close to the scalp"},
    {"type": "box braids", "country": "Africa", "description": "individual plaits divided by small squared-off parts"},
    {"type": "bun", "country": "neutral", "description": "hair pulled back and wrapped in a coil"},
    {"type": "french braid", "country": "France", "description": "three-strand braid woven from the crown"},
    {"type": "ponytail", "country": "neutral", "description": "hair pulled back and tied at the back of the head"},
    {"type": "chignon", "country": "France", "description": "low bun at the nape of the neck"},
    {"type": "dreadlocks", "country": "Jamaica", "description": "ropes of matted hair"},
    {"type": "top knot", "country": "Japan", "description": "high bun on the crown of the head"},
    {"type": "layered cut", "country": "neutral", "description": "hair cut in layers for volume"},
    {"type": "shag cut", "country": "neutral", "description": "layered, feathered cut"},
    {"type": "curly", "country": "neutral", "description": "natural or styled curls"},
    {"type": "straight", "country": "neutral", "description": "smooth, straight hair"},
    {"type": "wavy", "country": "neutral", "description": "loose, natural waves"},
    {"type": "fishtail braid", "country": "neutral", "description": "braid resembling a fish's tail"},
    {"type": "crown braid", "country": "neutral European", "description": "braid wrapped around the head like a crown"},
    {"type": "victory rolls", "country": "USA", "description": "rolled sections of hair, 1940s style"},
    {"type": "bouffant", "country": "France", "description": "puffed, high-volume style"},
    {"type": "mohawk", "country": "Native American", "description": "shaved sides with a strip of longer hair in the center"},
    {"type": "pageboy", "country": "neutral", "description": "straight hair with inward-curved ends"},
    {"type": "pigtails", "country": "neutral", "description": "two sections of hair tied on either side of the head"},
    {"type": "space buns", "country": "neutral", "description": "two buns on either side of the head"},
    {"type": "undercut", "country": "neutral", "description": "shaved or short sides with longer top"},
    {"type": "waterfall braid", "country": "neutral", "description": "braid with sections dropping down like a waterfall"},
    {"type": "twists", "country": "Africa", "description": "two-strand twisted sections"},
    {"type": "marley twists", "country": "Africa", "description": "twists using Marley hair extensions"},
    {"type": "faux locs", "country": "Africa", "description": "temporary dreadlock style"},
    {"type": "beehive", "country": "USA", "description": "tall, conical updo popular in the 1960s"},
    {"type": "finger waves", "country": "USA", "description": "S-shaped waves close to the scalp"},
    {"type": "pompadour", "country": "France", "description": "hair swept upwards from the face and worn high over the forehead"},
    {"type": "side shave", "country": "neutral", "description": "one side of the head shaved"},
    {"type": "half up half down", "country": "neutral", "description": "top section of hair pulled up, rest left down"},
    {"type": "messy bun", "country": "neutral", "description": "casual, loose bun"},
    {"type": "sleek ponytail", "country": "neutral", "description": "smooth, tight ponytail"},
    {"type": "Dutch braid", "country": "Netherlands", "description": "reverse French braid"},
    {"type": "Ghana braids", "country": "Ghana", "description": "cornrow style with extensions"},
    {"type": "Fulani braids", "country": "West Africa", "description": "braids with beads and accessories"},
    {"type": "Bantu knots", "country": "Africa", "description": "small, coiled buns"},
    {"type": "French twist", "country": "France", "description": "hair twisted upwards and tucked in"}
  ]
}
